moolib/_C.cpython-38-darwin.so
moolib/__init__.py
moolib/broker.py
moolib/examples/a2c.py
moolib/examples/atari_sweep.py
moolib/examples/minimal.py
moolib/examples/plot.py
moolib/examples/sbatch_experiment.py
moolib/examples/common/__init__.py
moolib/examples/common/nest.py
moolib/examples/common/record.py
moolib/examples/common/stats.py
moolib/examples/common/vtrace.py
moolib/examples/vtrace/__init__.py
moolib/examples/vtrace/atari_preprocessing.py
moolib/examples/vtrace/environment.py
moolib/examples/vtrace/envpool_venv.py
moolib/examples/vtrace/experiment.py
moolib/examples/vtrace/models.py
moolib-0.0.9b0.dist-info/LICENSE
moolib-0.0.9b0.dist-info/METADATA
moolib-0.0.9b0.dist-info/WHEEL
moolib-0.0.9b0.dist-info/top_level.txt
moolib-0.0.9b0.dist-info/RECORD
