Metadata-Version: 2.1
Name: moolib
Version: 0.0.9b0
Summary: A library for distributed ML training with PyTorch
Home-page: https://github.com/facebookresearch/moolib
Author: tscmoo & the moolib dev team
License: UNKNOWN
Platform: UNKNOWN
Classifier: Programming Language :: C++
Classifier: Programming Language :: Python :: 3
Classifier: License :: OSI Approved :: MIT License
Classifier: Operating System :: POSIX :: Linux
Classifier: Operating System :: MacOS :: MacOS X
Classifier: Environment :: GPU :: NVIDIA CUDA
Requires-Dist: torch (>=1.6.0)
